PingPongWr/PingPongWr.py
PingPongWr/__init__.py
PingPongWr-0.0.9.dist-info/LICENSE
PingPongWr-0.0.9.dist-info/METADATA
PingPongWr-0.0.9.dist-info/WHEEL
PingPongWr-0.0.9.dist-info/top_level.txt
PingPongWr-0.0.9.dist-info/RECORD
