Metadata-Version: 2.1
Name: PingPongWr
Version: 0.0.9
Summary: PingPongBuilder Custom Api Module
Home-page: UNKNOWN
Author: INIRU
Author-email: duswptkfkd59@naver.com
License: MIT
Keywords: pingpong,ping,pong,api
Platform: UNKNOWN
Requires-Python: >=3.8.0
Requires-Dist: aiohttp
